simpletap/apps.py
simpletap/auth.py
simpletap/backup.py
simpletap/config.py
simpletap/handlers.py
simpletap/ipc.py
simpletap/kernel.py
simpletap/naming.py
simpletap/package_manager.py
simpletap/profiles.py
simpletap/resources.py
simpletap/stcp.py
simpletap/streamer.py
simpletap_lib-2023.3.25.dist-info/LICENSE
simpletap_lib-2023.3.25.dist-info/METADATA
simpletap_lib-2023.3.25.dist-info/WHEEL
simpletap_lib-2023.3.25.dist-info/top_level.txt
simpletap_lib-2023.3.25.dist-info/RECORD
