Metadata-Version: 2.1
Name: simpletap-lib
Version: 2023.3.25
Summary: The SimpleTap core library
Author: Benjamin Mickler
License: GNU GENERAL PUBLIC LICENSE
Project-URL: Homepage, https://simpletap.benmickler.com
Project-URL: Source, https://git.benmickler.com/SimpleTap/simpletap
Project-URL: Bug Tracker, https://git.benmickler.com/SimpleTap/simpletap/issues
Classifier: Programming Language :: Python :: 3
Classifier: License :: OSI Approved :: GNU General Public License v3 or later (GPLv3+)
Classifier: Operating System :: POSIX :: Linux
Requires-Python: >=3.9
License-File: LICENSE
